nonebot_plugin_lxns_maimai-0.1.3.dist-info/METADATA
nonebot_plugin_lxns_maimai-0.1.3.dist-info/WHEEL
nonebot_plugin_lxns_maimai-0.1.3.dist-info/entry_points.txt
nonebot_plugin_lxns_maimai-0.1.3.dist-info/licenses/LICENSE
nonebot_plugin_lxns_maimai/__init__.py
nonebot_plugin_lxns_maimai/apis/__init__.py
nonebot_plugin_lxns_maimai/apis/request.py
nonebot_plugin_lxns_maimai/config.py
nonebot_plugin_lxns_maimai/exception.py
nonebot_plugin_lxns_maimai/filters.py
nonebot_plugin_lxns_maimai/migrations/ce7ee9d4e359_first_revision.py
nonebot_plugin_lxns_maimai/model.py
nonebot_plugin_lxns_maimai/render.py
nonebot_plugin_lxns_maimai/resources/fonts/SourceHanSans-Bold.otf
nonebot_plugin_lxns_maimai/resources/fonts/SourceHanSans-Heavy.otf
nonebot_plugin_lxns_maimai/resources/fonts/SourceHanSans-Medium.otf
nonebot_plugin_lxns_maimai/resources/fonts/SourceHanSans-Normal.otf
nonebot_plugin_lxns_maimai/resources/fonts/SourceHanSans-Regular.otf
nonebot_plugin_lxns_maimai/resources/images/canvas.png
nonebot_plugin_lxns_maimai/resources/images/default_icon.png
nonebot_plugin_lxns_maimai/resources/images/default_nameplate.png
nonebot_plugin_lxns_maimai/resources/templates/best50.html.jinja2
nonebot_plugin_lxns_maimai/resources/templates/icons.macros.html.jinja2
nonebot_plugin_lxns_maimai/resources/templates/index.css
nonebot_plugin_lxns_maimai/resources/templates/macros.html.jinja2
nonebot_plugin_lxns_maimai/schema/__init__.py
nonebot_plugin_lxns_maimai/schema/alias.py
nonebot_plugin_lxns_maimai/schema/collection.py
nonebot_plugin_lxns_maimai/schema/enum/__init__.py
nonebot_plugin_lxns_maimai/schema/enum/fctype.py
nonebot_plugin_lxns_maimai/schema/enum/fstype.py
nonebot_plugin_lxns_maimai/schema/enum/levelindex.py
nonebot_plugin_lxns_maimai/schema/enum/ratetype.py
nonebot_plugin_lxns_maimai/schema/enum/songtype.py
nonebot_plugin_lxns_maimai/schema/genre.py
nonebot_plugin_lxns_maimai/schema/notes.py
nonebot_plugin_lxns_maimai/schema/player.py
nonebot_plugin_lxns_maimai/schema/score.py
nonebot_plugin_lxns_maimai/schema/song.py
nonebot_plugin_lxns_maimai/schema/trend.py
nonebot_plugin_lxns_maimai/schema/version.py
nonebot_plugin_lxns_maimai/utils.py
nonebot_plugin_lxns_maimai-0.1.3.dist-info/RECORD
