Metadata-Version: 2.1
Name: nonebot-plugin-lxns-maimai
Version: 0.1.3
Summary: maimai DX 查分
Author-Email: KomoriDev <mute231010@gmail.com>
License: MIT
Requires-Python: >=3.10
Requires-Dist: nonebot2>=2.3.3
Requires-Dist: httpx>=0.27.0
Requires-Dist: nonebot-plugin-alconna>=0.52.0
Requires-Dist: nonebot-plugin-orm>=0.7.6
Requires-Dist: nonebot-plugin-user>=0.4.2
Requires-Dist: nonebot-plugin-htmlrender>=0.3.5
Provides-Extra: adapters
Requires-Dist: nonebot-adapter-onebot>=2.4.4; extra == "adapters"
